src_Verilog/lab1/decoder2_4.v
module decoder2_4_1 (
decode_in,
decode_out
);
input [1:0] decode_in;
output [3:0] decode_out;

//写出逻辑表达式，然后像卡诺图一样写出来
assign decode_out[0] = ~decode_in[1] & ~decode_in[0];
assign decode_out[1] = ~decode_in[1] & decode_in[0];
assign decode_out[2] = decode_in[1] & ~decode_in[0];
assign decode_out[3] = decode_in[1] & decode_in[0];

endmodule

module decoder2_4_2 (
decode_in,
decode_out
);
input [1:0] decode_in;
output [3:0] decode_out;

//用?:语句写
assign decode_out = decode_in[0] ? 
    (decode_in[1]? 4'b1000: 4'b0010):
    (decode_in[1]? 4'b0100: 4'b0001);

endmodule

module decoder2_4_3 (
decode_in,
decode_out
);
input [1:0] decode_in;
output reg [3:0] decode_out;

always @(*) begin //组合逻辑的always块写法，这样就可以用if-else或者case语句啦
    if (decode_in == 2'b00)
        decode_out = 4'b0001;
    else if (decode_in == 2'b01)
        decode_out = 4'b0010;
    else if (decode_in == 2'b10)
        decode_out = 4'b0100;
    else if (decode_in == 2'b11)
        decode_out = 4'b1000;
end

endmodule

src_Verilog/lab1/decoder2_4_tb_iverilog.v
`timescale 1ns/1ns
`include "decoder2_4.v"

module decoder_testbench;

reg [1:0] in;
wire [3:0] out1,out2,out3;

decoder2_4_1 dut0(
.decode_in      (in)
, .decode_out   (out1)
);

decoder2_4_2 dut1(
.decode_in      (in)
, .decode_out   (out2)
);

decoder2_4_3 dut2(
.decode_in      (in)
, .decode_out   (out3)
);

integer i; //integer is a 32b unsigned integer

initial begin
    // $monitor("time=%4d, in=%4b, out0=%04b, out1=%04b, out2=%04b", $time, in, out1, out2, out3);
    $monitor("%04x",out3);
    for(i=0; i<8; i=i+1) begin
        #10 in = i; 
    end
end

initial begin
    $dumpfile("wave.vcd");
    $dumpvars(0); //0 is to dump all variables; otherwise,e.g., 1 as the levels
end

endmodule

src_Verilog/lab1/wave.vcd
$date
	Thu Feb 22 17:39:49 2024
$end
$version
	Icarus Verilog
$end
$timescale
	1ns
$end
$scope module decoder_testbench $end
$var wire 4 ! out3 [3:0] $end
$var wire 4 " out2 [3:0] $end
$var wire 4 # out1 [3:0] $end
$var reg 2 $ in [1:0] $end
$var integer 32 % i [31:0] $end
$scope module dut0 $end
$var wire 2 & decode_in [1:0] $end
$var wire 4 ' decode_out [3:0] $end
$upscope $end
$scope module dut1 $end
$var wire 2 ( decode_in [1:0] $end
$var wire 4 ) decode_out [3:0] $end
$upscope $end
$scope module dut2 $end
$var wire 2 * decode_in [1:0] $end
$var reg 4 + decode_out [3:0] $end
$upscope $end
$upscope $end
$enddefinitions $end
$comment Show the parameter values. $end
$dumpall
$end
#0
$dumpvars
bx +
bx *
bx )
bx (
bx '
bx &
b0 %
bx $
bx #
bx "
bx !
$end
#10
b1 #
b1 '
b1 "
b1 )
b1 !
b1 +
b1 %
b0 $
b0 &
b0 (
b0 *
#20
b10 #
b10 '
b10 "
b10 )
b10 !
b10 +
b10 %
b1 $
b1 &
b1 (
b1 *
#30
b100 #
b100 '
b100 "
b100 )
b100 !
b100 +
b11 %
b10 $
b10 &
b10 (
b10 *
#40
b1000 #
b1000 '
b1000 "
b1000 )
b1000 !
b1000 +
b100 %
b11 $
b11 &
b11 (
b11 *
#50
b1 #
b1 '
b1 "
b1 )
b1 !
b1 +
b101 %
b0 $
b0 &
b0 (
b0 *
#60
b10 #
b10 '
b10 "
b10 )
b10 !
b10 +
b110 %
b1 $
b1 &
b1 (
b1 *
#70
b100 #
b100 '
b100 "
b100 )
b100 !
b100 +
b111 %
b10 $
b10 &
b10 (
b10 *
#80
b1000 #
b1000 '
b1000 "
b1000 )
b1000 !
b1000 +
b1000 %
b11 $
b11 &
b11 (
b11 *
