src_Verilog/lab2/p1/dff.v
module dff_sync_reset (
data   , // Data Input
clk    , // Clock Input
reset  , // Reset input
q        // Q output
);

input data, clk, reset ; //Input Ports

output reg q;//Output Ports

always @ ( posedge clk)
if (reset) begin
  q <= 1'b0;
end  else begin
  q <= data;
end

endmodule

module dff_async_reset (
data   , // Data Input
clk    , // Clock Input
reset  , // Reset input
q        // Q output
);

input data, clk, reset ; //Input Ports

output reg q;//Output Ports

always @ ( posedge clk or posedge reset)
if (reset) begin
  q <= 1'b0;
end  else begin
  q <= data;
end

endmodule

module dlatch_reset (
data   , // Data Input
en     , // LatchInput
reset  , // Reset input
q        // Q output
);

input data, en, reset ; //Input Ports

output reg q; //Output Ports

always @ ( en or reset or data)
if (reset) begin
  q <= 1'b0;
end else if (en) begin
  q <= data;
end

endmodule

src_Verilog/lab2/p1/dff_tb.v
`timescale 1ns/1ns
`include "dff.v"

module dff_tb;

reg d,clk,rst;
wire q1,q2,q3;

initial begin
    $dumpfile("wave.vcd");
    $dumpvars(0);
    $monitor("time=%4t, d=%2b, clk=%2b, rst=%2b, q1=%2b, q2=%2b, q3=%2b",$time,d,clk,rst,q1,q2,q3);
end

initial clk = 0;
always #5 clk = ~clk;

initial begin
    rst = 0;
    #1 rst = 1;
    #10 rst = 0;
    #25 rst = 1;
    #1 rst = 0;
end

initial begin
    d = 0;
    #10 d = 1;
    #7 d = 0;
    #1 d = 1;
    #3 d = 0;
    #1 d = 1;
    #1 d = 0;
    #10 d = 1;
    #10 $finish;
end

dff_sync_reset dut1(
.data   (d)   ,// Data Input
.clk    (clk) ,// Clock Input
.reset  (rst) ,// Reset input
.q      (q1)    // Q output
);


dff_async_reset dut2(
.data   (d)   ,// Data Input
.clk    (clk) ,// Clock Input
.reset  (rst) ,// Reset input
.q      (q2)    // Q output
);

dlatch_reset dut3(
.data (d)   , // Data Input
.en (clk)     , // LatchInput
.reset (rst)  , // Reset input
.q (q3)        // Q output
);

endmodule

src_Verilog/lab2/p1/wave.vcd
$date
	Sat Feb 10 11:27:52 2024
$end
$version
	Icarus Verilog
$end
$timescale
	1ns
$end
$scope module dff_tb $end
$var wire 1 ! q3 $end
$var wire 1 " q2 $end
$var wire 1 # q1 $end
$var reg 1 $ clk $end
$var reg 1 % d $end
$var reg 1 & rst $end
$scope module dut1 $end
$var wire 1 $ clk $end
$var wire 1 % data $end
$var wire 1 & reset $end
$var reg 1 # q $end
$upscope $end
$scope module dut2 $end
$var wire 1 $ clk $end
$var wire 1 % data $end
$var wire 1 & reset $end
$var reg 1 " q $end
$upscope $end
$scope module dut3 $end
$var wire 1 % data $end
$var wire 1 $ en $end
$var wire 1 & reset $end
$var reg 1 ! q $end
$upscope $end
$upscope $end
$enddefinitions $end
$comment Show the parameter values. $end
$dumpall
$end
#0
$dumpvars
0&
0%
0$
x#
x"
x!
$end
#1
0"
0!
1&
#5
0#
1$
#10
0$
1%
#11
0&
#15
1#
1"
1!
1$
#17
0!
0%
#18
1!
1%
#20
0$
#21
0%
#22
1%
#23
0%
#25
0#
0"
0!
1$
#30
0$
#33
1%
#35
1#
1"
1!
1$
#36
0"
0!
1&
#37
1!
0&
